{
"type": "FeatureCollection",
"name": "Kawasan Terdampak",
"crs": { "type": "name", "properties": { "name": "urn:ogc:def:crs:OGC:1.3:CRS84" } },
"features": [
{ "type": "Feature", "properties": { "Id": 0, "Bencana": "Banjir", "Alamat": "RW 03", "Penyebab": "Hujan Deras, Peninggian Jalan, dan Belum Ada Pompa" }, "geometry": { "type": "Point", "coordinates": [ 110.389873981000051, -6.978936194999968 ] } },
{ "type": "Feature", "properties": { "Id": 0, "Bencana": "Banjir", "Alamat": "RW 03", "Penyebab": "Hujan Deras, Peninggian Jalan, dan Belum Ada Pompa" }, "geometry": { "type": "Point", "coordinates": [ 110.390229419080555, -6.9794391528722 ] } },
{ "type": "Feature", "properties": { "Id": 0, "Bencana": "Banjir", "Alamat": "RW 01", "Penyebab": "Hujan Deras dan Pompa Air Tidak Berfungsi" }, "geometry": { "type": "Point", "coordinates": [ 110.393555190136311, -6.978533989502095 ] } },
{ "type": "Feature", "properties": { "Id": 0, "Bencana": "Banjir", "Alamat": "RW 02", "Penyebab": "Hujan Deras dan Resapan Air Kurang Maksimal" }, "geometry": { "type": "Point", "coordinates": [ 110.391830137655589, -6.980123263011922 ] } },
{ "type": "Feature", "properties": { "Id": 0, "Bencana": "Banjir", "Alamat": "RW 02", "Penyebab": "Hujan Deras dan Resapan Air Kurang Maksimal" }, "geometry": { "type": "Point", "coordinates": [ 110.391926342188512, -6.980560604002443 ] } },
{ "type": "Feature", "properties": { "Id": 0, "Bencana": "Banjir", "Alamat": "RW 01", "Penyebab": "Hujan Deras" }, "geometry": { "type": "Point", "coordinates": [ 110.39388656602496, -6.980491876585207 ] } },
{ "type": "Feature", "properties": { "Id": 0, "Bencana": "Banjir", "Alamat": "RW 01", "Penyebab": "Hujan Deras" }, "geometry": { "type": "Point", "coordinates": [ 110.393790006521343, -6.980856657056017 ] } },
{ "type": "Feature", "properties": { "Id": 0, "Bencana": "Banjir", "Alamat": "RW 01", "Penyebab": "Hujan Deras dan Pompa Air Tidak Berfungsi" }, "geometry": { "type": "Point", "coordinates": [ 110.393678100000045, -6.978981699999956 ] } },
{ "type": "Feature", "properties": { "Id": 0, "Bencana": "Banjir", "Alamat": "RW 01", "Penyebab": "Hujan Deras dan Pompa Air Tidak Berfungsi" }, "geometry": { "type": "Point", "coordinates": [ 110.393647876514734, -6.979358949585892 ] } },
{ "type": "Feature", "properties": { "Id": 0, "Bencana": "Banjir", "Alamat": "RW 05", "Penyebab": "Hujan Deras dan Drainase Tidak Lancar" }, "geometry": { "type": "Point", "coordinates": [ 110.392223803443542, -6.978247475681887 ] } },
{ "type": "Feature", "properties": { "Id": 0, "Bencana": "Banjir", "Alamat": "RW 04", "Penyebab": "Hujan Deras dan Saluran Tersumbat" }, "geometry": { "type": "Point", "coordinates": [ 110.393722600627129, -6.978075002904633 ] } },
{ "type": "Feature", "properties": { "Id": 0, "Bencana": "Banjir", "Alamat": "RW 05", "Penyebab": "Hujan Deras dan Drainase Tidak Lancar" }, "geometry": { "type": "Point", "coordinates": [ 110.391987539406429, -6.977577051074561 ] } },
{ "type": "Feature", "properties": { "Id": 0, "Bencana": "Banjir", "Alamat": "RW 05", "Penyebab": "Hujan Deras dan Peninggian Jalan" }, "geometry": { "type": "Point", "coordinates": [ 110.391797020111454, -6.976724795530448 ] } },
{ "type": "Feature", "properties": { "Id": 0, "Bencana": "Banjir", "Alamat": "RW 05", "Penyebab": "Hujan Deras dan Peninggian Jalan" }, "geometry": { "type": "Point", "coordinates": [ 110.391869877548004, -6.975949464441401 ] } },
{ "type": "Feature", "properties": { "Id": 0, "Bencana": "Banjir", "Alamat": "RW 06", "Penyebab": "Hujan Deras dan Pompa Air Tidak Berfungsi" }, "geometry": { "type": "Point", "coordinates": [ 110.389216319661301, -6.975673204393009 ] } },
{ "type": "Feature", "properties": { "Id": 0, "Bencana": "Banjir", "Alamat": "RW 06", "Penyebab": "Hujan Deras dan Pompa Air Tidak Berfungsi" }, "geometry": { "type": "Point", "coordinates": [ 110.390126168525683, -6.976058132303242 ] } }
]
}
